subsampwinner/GenerateData.py
subsampwinner/SubsampDoubleAssurance.py
subsampwinner/__init__.py
subsampwinner/subsamp.py
subsampwinner-0.0.8.dist-info/LICENSE
subsampwinner-0.0.8.dist-info/METADATA
subsampwinner-0.0.8.dist-info/WHEEL
subsampwinner-0.0.8.dist-info/top_level.txt
subsampwinner-0.0.8.dist-info/RECORD
