Metadata-Version: 2.1
Name: subsampwinner
Version: 0.0.8
Summary: A package for feature selection using Subsampling Winner Algorithm
Home-page: https://github.com/wdai0/subsamp
Author: Wei Dai
Author-email: wdai@gmu.edu
Classifier: Development Status :: 3 - Alpha
Classifier: Intended Audience :: Science/Research
Classifier: License :: OSI Approved :: MIT License
Classifier: Programming Language :: Python :: 3
Classifier: Programming Language :: Python :: 3.7
Classifier: Programming Language :: Python :: 3.8
Classifier: Programming Language :: Python :: 3.9
Classifier: Programming Language :: Python :: 3.10
Requires-Python: >=3.7
License-File: LICENSE
Requires-Dist: numpy>=1.26.4
Requires-Dist: scipy>=1.13.0
Requires-Dist: statsmodels>=0.14.2
Requires-Dist: mpi4py>=3.1.6
